YunduanShejiYuShijianSaipao/README.md
YunduanShejiYuShijianSaipao/__init__.py
YunduanShejiYuShijianSaipao/__main__.py
YunduanShejiYuShijianSaipao/file.pdf
YunduanShejiYuShijianSaipao/index.html
yunduan_sheji_yu_shijian_saipao-2024.3.6.0.dist-info/METADATA
yunduan_sheji_yu_shijian_saipao-2024.3.6.0.dist-info/WHEEL
yunduan_sheji_yu_shijian_saipao-2024.3.6.0.dist-info/entry_points.txt
yunduan_sheji_yu_shijian_saipao-2024.3.6.0.dist-info/top_level.txt
yunduan_sheji_yu_shijian_saipao-2024.3.6.0.dist-info/RECORD
